LICENSE
README.md
setup.py
tartiflette_plugin_scalars/__init__.py
tartiflette_plugin_scalars/big_int.py
tartiflette_plugin_scalars/datetime.py
tartiflette_plugin_scalars/duration.py
tartiflette_plugin_scalars/email_address.py
tartiflette_plugin_scalars/geo_json.py
tartiflette_plugin_scalars/guid.py
tartiflette_plugin_scalars/hex_color_code.py
tartiflette_plugin_scalars/hsl.py
tartiflette_plugin_scalars/hsla.py
tartiflette_plugin_scalars/ipv4.py
tartiflette_plugin_scalars/ipv6.py
tartiflette_plugin_scalars/isbn.py
tartiflette_plugin_scalars/json.py
tartiflette_plugin_scalars/json_object.py
tartiflette_plugin_scalars/long.py
tartiflette_plugin_scalars/mac.py
tartiflette_plugin_scalars/naive_datetime.py
tartiflette_plugin_scalars/negative_float.py
tartiflette_plugin_scalars/negative_int.py
tartiflette_plugin_scalars/non_negative_float.py
tartiflette_plugin_scalars/non_negative_int.py
tartiflette_plugin_scalars/non_positive_float.py
tartiflette_plugin_scalars/non_positive_int.py
tartiflette_plugin_scalars/phone_number.py
tartiflette_plugin_scalars/port.py
tartiflette_plugin_scalars/positive_float.py
tartiflette_plugin_scalars/positive_int.py
tartiflette_plugin_scalars/postal_code.py
tartiflette_plugin_scalars/rgb.py
tartiflette_plugin_scalars/rgba.py
tartiflette_plugin_scalars/unsigned_int.py
tartiflette_plugin_scalars/url.py
tartiflette_plugin_scalars/us_currency.py
tartiflette_plugin_scalars/uuid.py
tartiflette_plugin_scalars.egg-info/PKG-INFO
tartiflette_plugin_scalars.egg-info/SOURCES.txt
tartiflette_plugin_scalars.egg-info/dependency_links.txt
tartiflette_plugin_scalars.egg-info/requires.txt
tartiflette_plugin_scalars.egg-info/top_level.txt