Metadata-Version: 2.1
Name: tartiflette-plugin-scalars
Version: 0.3.1
Summary: Tartiflette plugin providing common scalars
Home-page: https://github.com/dailymotion/tartiflette-plugin-scalars
Author: Alice Girard Guittard
Author-email: alice.girardguittard@dailymotion.com
License: MIT
Keywords: api graphql protocol tartiflette
Platform: UNKNOWN
Classifier: Intended Audience :: Developers
Classifier: Topic :: Software Development :: Libraries
Classifier: Programming Language :: Python :: 3.6
Classifier: Programming Language :: Python :: Implementation :: PyPy
Provides-Extra: test
License-File: LICENSE
